[
    {
        "level": 1,
        "ability_score_improvement": false,
        "proficiency": 2
      },
      {
        "level": 2,
        "ability_score_improvement": false,
        "proficiency": 2
      },
      {
        "level": 3,
        "ability_score_improvement": false,
        "proficiency": 2
      },
      {
        "level": 4,
        "ability_score_improvement": true,
        "proficiency": 2
      },
      {
        "level": 5,
        "ability_score_improvement": false,
        "proficiency": 3
      },
      {
        "level": 6,
        "ability_score_improvement": false,
        "proficiency": 3
      },
      {
        "level": 7,
        "ability_score_improvement": false,
        "proficiency": 3
      },
      {
        "level": 8,
        "ability_score_improvement": true,
        "proficiency": 3
      },
      {
        "level": 9,
        "ability_score_improvement": false,
        "proficiency": 4
      },
      {
        "level": 10,
        "ability_score_improvement": false,
        "proficiency": 4
      }
]